setup.py
bundleband/__init__.py
bundleband/client.py
bundleband/client_errors.py
bundleband/client_start.py
bundleband/handlers.py
bundleband/server.py
bundleband.egg-info/PKG-INFO
bundleband.egg-info/SOURCES.txt
bundleband.egg-info/dependency_links.txt
bundleband.egg-info/top_level.txt
bundleband/jim/__init__.py
bundleband/jim/config.py
bundleband/jim/errors.py
bundleband/jim/protocol.py
bundleband/jim/test_protocol.py
bundleband/log/__init__.py
bundleband/log/client_log_config.py
bundleband/log/decorators.py
bundleband/log/server_log_config.py
bundleband/log/test_decorators.py
bundleband/repo/__init__.py
bundleband/repo/client_errors.py
bundleband/repo/client_models.py
bundleband/repo/client_repo.py
bundleband/repo/repo.py
bundleband/repo/server_errors.py
bundleband/repo/server_models.py
bundleband/repo/server_repo.py