Metadata-Version: 1.0
Name: bundleband
Version: 0.0.6
Summary: client-server chat with clients gui for bundleband project
Home-page: https://github.com/OOPSA45/Python-learn-
Author: Kirill Komarov
Author-email: k.komv@ya.ru
License: UNKNOWN
Platform: UNKNOWN
